tibber_pulse_sml_debugger/__init__.py
tibber_pulse_sml_debugger/exceptions.py
tibber_pulse_sml_debugger/helper.py
tibber_pulse_sml_debugger/main.py
tibber_pulse_sml_debugger-1.0.3.dist-info/METADATA
tibber_pulse_sml_debugger-1.0.3.dist-info/WHEEL
tibber_pulse_sml_debugger-1.0.3.dist-info/entry_points.txt
tibber_pulse_sml_debugger-1.0.3.dist-info/licenses/LICENSE
tibber_pulse_sml_debugger-1.0.3.dist-info/RECORD
