Metadata-Version: 2.4
Name: tibber-pulse-sml-debugger
Version: 1.0.3
Summary: A tiny python based CLI application to see the data, that was recorded and send by your Tibber Pulse IR to your Tibber Pulse Bridge.
Project-URL: Homepage, https://codeberg.org/wh0ami/tibber-pulse-sml-debugger
Project-URL: Documentation, https://codeberg.org/wh0ami/tibber-pulse-sml-debugger/src/branch/master/README.md
Project-URL: Repository, https://codeberg.org/wh0ami/tibber-pulse-sml-debugger
Project-URL: Issues, https://codeberg.org/wh0ami/tibber-pulse-sml-debugger/issues
Author-email: wh0ami <wh0ami@noreply.codeberg.org>
License: Copyright (c) 2024 wh0ami
License-File: LICENSE
Keywords: SML,Tibber,debug,electric,energy,pulse
Classifier: Development Status :: 5 - Production/Stable
Classifier: Environment :: Console
Classifier: License :: OSI Approved :: MIT License
Classifier: Programming Language :: Python :: 3
Requires-Python: >=3.10
Requires-Dist: loguru>=0.7.3
Requires-Dist: requests>=2.32.3
Requires-Dist: smllib>=1.5
